{
  "$schema": "https://json-schema.org/draft/2020-12/schema",
  "$id": "https://ucp.dev/schemas/shopping/checkout.complete_req.json",
  "name": "dev.ucp.shopping.checkout",
  "version": "2026-01-11",
  "title": "Checkout Complete Request",
  "description": "Base checkout schema. Extensions compose onto this using allOf.",
  "type": "object",
  "required": [
    "payment"
  ],
  "additionalProperties": true,
  "properties": {
    "payment": {
      "$ref": "https://ucp.dev/schemas/shopping/payment.json"
    }
  }
}